waldur_auth_valimo/__init__.py
waldur_auth_valimo/admin.py
waldur_auth_valimo/apps.py
waldur_auth_valimo/client.py
waldur_auth_valimo/executors.py
waldur_auth_valimo/extension.py
waldur_auth_valimo/filters.py
waldur_auth_valimo/models.py
waldur_auth_valimo/serializers.py
waldur_auth_valimo/tasks.py
waldur_auth_valimo/urls.py
waldur_auth_valimo/views.py
waldur_auth_valimo/migrations/0001_initial.py
waldur_auth_valimo/migrations/__init__.py
waldur_auth_valimo-0.2.0.dist-info/DESCRIPTION.rst
waldur_auth_valimo-0.2.0.dist-info/METADATA
waldur_auth_valimo-0.2.0.dist-info/RECORD
waldur_auth_valimo-0.2.0.dist-info/WHEEL
waldur_auth_valimo-0.2.0.dist-info/entry_points.txt
waldur_auth_valimo-0.2.0.dist-info/metadata.json
waldur_auth_valimo-0.2.0.dist-info/top_level.txt
