Metadata-Version: 2.0
Name: waldur-auth-valimo
Version: 0.2.0
Summary: Mobile phone authentication using Valimo PKI.
Home-page: http://waldur.com
Author: OpenNode Team
Author-email: info@opennodecloud.com
License: MIT
Platform: UNKNOWN
Classifier: Framework :: Django
Classifier: Intended Audience :: Developers
Classifier: Intended Audience :: System Administrators
Classifier: Operating System :: OS Independent
Classifier: License :: OSI Approved :: MIT License
Requires-Dist: lxml (>=3.2.0)
Requires-Dist: nodeconductor (>=0.107.0)
Provides-Extra: dev
Requires-Dist: Sphinx (==1.2.2); extra == 'dev'
